mamo/__init__.py
mamo/api_support.py
mamo/internal/__init__.py
mamo/internal/bimap.py
mamo/internal/cached_values.py
mamo/internal/db_stored_value.py
mamo/internal/default_module_extension.py
mamo/internal/delayed_interruption_context.py
mamo/internal/fingerprint_registry.py
mamo/internal/fingerprints.py
mamo/internal/function_registry.py
mamo/internal/identities.py
mamo/internal/identity_registry.py
mamo/internal/main.py
mamo/internal/module_extension.py
mamo/internal/persisted_store.py
mamo/internal/providers.py
mamo/internal/reflection.py
mamo/internal/result_metadata.py
mamo/internal/result_registry.py
mamo/internal/staleness_registry.py
mamo/internal/stopwatch_context.py
mamo/internal/value_provider_mediator.py
mamo/internal/value_registries.py
mamo/internal/weakref_utils.py
mamo/internal/common/__init__.py
mamo/internal/common/id_set.py
mamo/internal/common/key_id_dict.py
mamo/support/__init__.py
mamo/support/ipython.py
mamo/support/numpy.py
mamo/support/torch.py
mamo-0.1.3.dist-info/LICENSE
mamo-0.1.3.dist-info/METADATA
mamo-0.1.3.dist-info/WHEEL
mamo-0.1.3.dist-info/top_level.txt
mamo-0.1.3.dist-info/RECORD
