Metadata-Version: 2.1
Name: mamo
Version: 0.1.3
Summary: A big flappy cache that never forgets.
Home-page: https://github.com/blackhc/mamo
Author: Andreas @blackhc Kirsch
Author-email: blackhc+mamo@gmail.com
License: MIT
Keywords: tools memoization data
Platform: UNKNOWN
Classifier: Development Status :: 3 - Alpha
Classifier: Intended Audience :: Developers
Classifier: Intended Audience :: Science/Research
Classifier: Topic :: Software Development :: Libraries :: Python Modules
Classifier: License :: OSI Approved :: MIT License
Classifier: Programming Language :: Python :: 3.7
Requires-Dist: ZODB
Requires-Dist: objproxies
Requires-Dist: persistent
Requires-Dist: pathvalidate
Provides-Extra: dev
Requires-Dist: check-manifest ; extra == 'dev'
Requires-Dist: numpy ; extra == 'dev'
Requires-Dist: torch (<2) ; extra == 'dev'
Provides-Extra: test
Requires-Dist: coverage (<5) ; extra == 'test'
Requires-Dist: codecov ; extra == 'test'
Requires-Dist: pytest ; extra == 'test'
Requires-Dist: pytest-runner ; extra == 'test'
Requires-Dist: pytest-benchmark ; extra == 'test'
Requires-Dist: pytest-cov ; extra == 'test'
